Metadata-Version: 1.0
Name: LifeGame
Version: 1.0.3
Summary: Conway's Game of Life in Python.
Home-page: https://github.com/Oscarozo/GameofLife
Author: Oscar Ozorio
Author-email: osvaldo15963@fpuna.edu.py
License: GPL-3.0
Platform: UNKNOWN
